starling_beancount/__init__.py
starling_beancount/extractor.py
starling_beancount/importer.py
starling_beancount/py.typed
starling_beancount/utils.py
starling_beancount-2.0.1.dist-info/LICENSE
starling_beancount-2.0.1.dist-info/METADATA
starling_beancount-2.0.1.dist-info/WHEEL
starling_beancount-2.0.1.dist-info/entry_points.txt
starling_beancount-2.0.1.dist-info/top_level.txt
starling_beancount-2.0.1.dist-info/RECORD
