Metadata-Version: 2.2
Name: starling-beancount
Version: 2.0.1
Summary: Import Starling Bank transactions in Beancount
Author-email: Chris Arderne <chris@rdrn.me>
License: MIT License
Project-URL: homepage, https://github.com/carderne/starling-beancount
Keywords: accounting,cli,beancount,banking
Classifier: Environment :: Console
Classifier: License :: OSI Approved :: MIT License
Classifier: Operating System :: Unix
Classifier: Programming Language :: Python
Requires-Python: >=3.10
License-File: LICENSE
Requires-Dist: beancount>=3.1.0
Requires-Dist: httpx>=0.28.1
Requires-Dist: python-dateutil>=2.9.0.post0
Requires-Dist: PyYAML>=6.0.2
Requires-Dist: typer>=0.15.0
